{
  "ticket_symbols": [
    {
      "id": "AAPL"
    },
    {
      "id": "GOOGL"
    },
    {
      "id": "TSLA"
    },
    {
      "id": "IREN"
    },
    {
      "id": "JPM"
    },
    {
      "id": "AMZN"
    }
  ],
  "categories": [
    {
      "id": "Culture"
    },
    {
      "id": "Passion"
    },
    {
      "id": "Leadership"
    }
  ],
  "users": [
    {
      "id": "23881380",
      "surname": "wang",
      "emplid": "23881380",
      "class_code": "CSE 110",
      "score": 0,
      "reports_symbols": [
        "AAPL",
        "GOOGL",
        "TSLA"
      ]
    },
    {
      "id": "23881381",
      "surname": "wang",
      "emplid": "23881381",
      "class_code": "CSE 110",
      "score": 0,
      "reports_symbols": [
        "GOOGL",
        "IREN",
        "JPM"
      ]
    }
  ],
  "phrases": [
    {
      "id": "1",
      "keyword": "Culture Maniac",
      "reason": "This is a great phrase to use in the workplace to describe someone who is passionate about the company culture and is always looking for ways to improve it.",
      "quote": "I am a culture maniac and I am always looking for ways to improve the company culture.",
      "categories": [
        "Culture",
        "Passion"
      ],
      "weight": "1",
      "user_id": "1",
      "timestamp": "2022-01-01T00:00:00.000Z",
      "symbol": "APPL",
      "table_id": "1"
    },
    {
      "id": "e2ae",
      "keyword": "Key",
      "quote": "Qutes",
      "reason": "Reaon",
      "categories": [
        "Culture"
      ],
      "weight": "23",
      "user_id": "23881380",
      "symbol": "GOOGL",
      "table_id": "1"
    },
    {
      "id": "b9ed",
      "keyword": "testad",
      "quote": "1213",
      "reason": "sadasdsa",
      "categories": [
        "Culture"
      ],
      "weight": "023",
      "user_id": "23881380",
      "symbol": "GOOGL",
      "table_id": "1"
    },
    {
      "id": "030e",
      "keyword": "213213",
      "quote": "12321",
      "reason": "12312",
      "categories": [
        "Leadership"
      ],
      "weight": "213",
      "user_id": "23881380",
      "symbol": "GOOGL",
      "table_id": "1"
    },
    {
      "id": "7ae7",
      "keyword": "asdas",
      "quote": "21321",
      "reason": "asd",
      "categories": [
        "Leadership"
      ],
      "weight": "2",
      "user_id": "23881380",
      "symbol": "GOOGL",
      "table_id": "1"
    },
    {
      "id": "c1a5",
      "keyword": "Report",
      "quote": "Quote Reports",
      "reason": "Notes Report",
      "categories": [
        "Leadership"
      ],
      "weight": "3",
      "user_id": "23881380",
      "symbol": "AAPL",
      "table_id": "1"
    },
    {
      "id": "f1e0",
      "keyword": "tesad",
      "quote": "saasd",
      "reason": "asda",
      "categories": [
        "Culture"
      ],
      "weight": "2",
      "user_id": "23881380",
      "symbol": "GOOGL",
      "table_id": "23881380GOOGL"
    },
    {
      "id": "d6c7",
      "keyword": "Another Keyword",
      "quote": "asdas",
      "reason": "Reason2",
      "categories": [
        "Culture"
      ],
      "weight": "2",
      "user_id": "23881380",
      "symbol": "GOOGL",
      "table_id": "23881380GOOGL"
    },
    {
      "id": "26cd",
      "keyword": "asd",
      "quote": "asdasd",
      "reason": "asdasd",
      "categories": [
        "Leadership",
        "Culture"
      ],
      "weight": "3",
      "user_id": "23881380",
      "symbol": "GOOGL",
      "table_id": "23881380GOOGL"
    },
    {
      "id": "8ec3",
      "keyword": "Some apple keyword",
      "quote": "asds",
      "reason": "I like it",
      "categories": [
        "Culture"
      ],
      "weight": "123",
      "user_id": "23881380",
      "symbol": "AAPL",
      "table_id": "23881380AAPL"
    },
    {
      "id": "8ae6",
      "keyword": "asd",
      "quote": "aple",
      "reason": "asd",
      "categories": [
        "Leadership"
      ],
      "weight": "23",
      "user_id": "23881380",
      "symbol": "AAPL",
      "table_id": "23881380AAPL"
    },
    {
      "id": "58d0",
      "keyword": "asdas",
      "quote": "asdas",
      "reason": "asdas",
      "categories": [
        "Leadership"
      ],
      "weight": "213",
      "user_id": "23881380",
      "symbol": "GOOGL",
      "table_id": "23881380GOOGL"
    },
    {
      "id": "6844"
    }
  ],
  "tables": [
    {
      "id": "1",
      "symbol": "APPL",
      "user_id": "1"
    },
    {
      "id": "23881380AAPL",
      "symbol": "AAPL",
      "user_id": "23881380"
    },
    {
      "id": "23881380GOOGL",
      "symbol": "GOOGL",
      "user_id": "23881380"
    },
    {
      "id": "23881380TSLA",
      "symbol": "TSLA",
      "user_id": "23881380"
    },
    {
      "id": "23881381GOOGL",
      "symbol": "GOOGL",
      "user_id": "23881381"
    },
    {
      "id": "23881381IREN",
      "symbol": "IREN",
      "user_id": "23881381"
    },
    {
      "id": "23881381JPM",
      "symbol": "JPM",
      "user_id": "23881381"
    },
    {
      "id": "23881382AMZN",
      "symbol": "AMZN",
      "user_id": "23881382"
    }
  ]
}